{
  "name": "Elnora Nelson",
  "age": 51,
  "address": {
    "street": "Viprat Lane",
    "city": "Cowdogra",
    "state": "SD",
    "zip": "92457"
  },
  "contact": {
    "phone": "(880) 244-3510",
    "servicePhone": "800436219"
  },
  "birthday": "1979-09-25T23:11:15.511Z",
  "ip": "225.30.183.105",
  "foo": "bar",
  "profile": {
    "about": "Ho kujnujwa wud ef ge dezcu hihol jil hoh caomisez gijjut lubuhibe. Umahiov ovu zelze vufioci rigze aj falogza kebi fas gajjarsek dideji toter si awe iv. Ra ebbe ga uwoosu dofe mobe nahnowpi roju cetiva ab fu rav. Kusfoha cehbukoco zadavsiz cahin umti se le sitruhib kabjunob umo uc nus gen nosatcu zocuci egaetgaj degos nejzum.",
    "bio": "Cenour ezaviw resa pohta pefkuv zibresoh jo tor tavpujgu heloag pegu kula jac rogugus aceto katfew ige bur. Vitiin puesuw ovoag fu hajsuj go neipi naigo hepa umefi peljuz temavok. Uw japcevmoj pefpu ahwel kejzab ulijez pugdisi sek sud vev posurapi guw elde. Sevil ulusu juvmas uwu pizgok livba jecilhos hoalifa wimena onoj cez hole uw medbu caoc hi zera. Idohvir cikizmu fehvuw hiz jatozdo ginwuhoj macip cekujko dusfaj pazragi lewuga tebof imu nuaza tebfikid rauk. Kamvat cubrirazo je riga kilucvu ne uhoog amna fuk vi tap gemba guv. Lumedci sato na puoteso omzilkul ab wuc fatockug zioke ga pec womba ohe kidabhib."
  },
  "apiKey": "0ece2199f7328a5aa9f667649ababbcfa0ed20c5d8daf606ba10e120fa2c67ff",
  "currency": {
    "code": "RUB",
    "name": "Russia Ruble"
  }
}