{
  "name": "Sadie Casey",
  "age": 63,
  "address": {
    "street": "Odala Circle",
    "city": "Fahrare",
    "state": "RI",
    "zip": "62649"
  },
  "contact": {
    "phone": "(728) 687-1029",
    "servicePhone": "800299823"
  },
  "birthday": "2000-04-29T20:58:30.126Z",
  "ip": "181.119.109.1",
  "foo": "bar",
  "profile": {
    "about": "Obeofwi higef loku wul narow tasibwed wa wap decebrez op rejjocza piliglav jo. Vire fikze umalef wahzi ogbam ot uwris gew bajupmem so lijjerdi juftib akedeju daopacaw gizum ucemesnog wuese cut. Javwi vohokle regom lu zafudjel cohlalguf pegpode nupor aronve eflosip orekli diitu uwu rarzu purow. Isse ewda cidjeh abisundat ile nezdib kekdufak sarerpo ase neode lighi ujtifiku alupitaho rehazkak cerle wa bofho. Lebsonewe kinnaeku mo reoru wawu fawelvo zakag urnibub zopul mutiapi go mug miklu davimi wiselo luflas nusdib. Ajahal naafa esitu ozo ubutar negtoalu lu ozwidke sinuseg danji kiv pom omiw.",
    "bio": "Tak hohguozo ok boduv berpi ja nomowvip nekeec hi to zuc ol bato. Va eja dunmimrul hagomu ero mir fivu apahi zecenesu hizame em eb tarfe idiwof. Fa vaawo lakef hoc moemu joowane paji gungo teit catjovkac ulu ripijikor lunofe. Gadru vac labifab jojwo gebbah vuuribu rapvi cupza nosatedi motnor ko de vertirfu me."
  },
  "apiKey": "12a10eb113a320fd2b4f600d11d22b74054e8660939c75c5041e1491caee7394",
  "currency": {
    "code": "MWK",
    "name": "Malawi Kwacha"
  }
}